HPGO-0.9.2.dist-info/METADATA
HPGO-0.9.2.dist-info/WHEEL
HPGO.cpython-37m-x86_64-linux-gnu.so
HPGO-0.9.2.dist-info/RECORD
