Metadata-Version: 2.1
Name: HPGO
Version: 0.9.2
Requires-Dist: graphviz~=0.13
Summary: Hybrid Parallelism Global Orchestration
Author: Yi Rong <hi@rongyi.io>
Author-Email: Yi Rong <hi@rongyi.io>
License: BSD-3-Clause
